./.gitignore
./.replit
./LICENSE
./PKG-INFO
./Pipfile
./Pipfile.lock
./README.md
./passage_of_time_mcp.py
./pyproject.toml
./docs/screenshot-0.png
./docs/screenshot-5a.png
./docs/screenshot-5b.png
./docs/screenshot-5c.png
./tests/test_passage_of_time_mcp.py
iflow_mcp_jlumbroso_passage_of_time_mcp-0.1.0.dist-info/METADATA
iflow_mcp_jlumbroso_passage_of_time_mcp-0.1.0.dist-info/WHEEL
iflow_mcp_jlumbroso_passage_of_time_mcp-0.1.0.dist-info/entry_points.txt
iflow_mcp_jlumbroso_passage_of_time_mcp-0.1.0.dist-info/licenses/LICENSE
iflow_mcp_jlumbroso_passage_of_time_mcp-0.1.0.dist-info/RECORD
