Metadata-Version: 2.4
Name: iflow-mcp_jlumbroso_passage-of-time-mcp
Version: 0.1.0
Summary: An MCP server that gives language models temporal awareness and time calculation abilities
License-File: LICENSE
Requires-Python: >=3.12
Requires-Dist: fastmcp>=0.1.0
Requires-Dist: python-dateutil>=2.8.2
Requires-Dist: pytz>=2024.1
